{
  "addresses": {
    "admin": "GedWR7tUUKy9aMmA4dH3sd9MZmhLAB7RrbbDtKQnw2if",
    "lpTokenMint": "ALP89a89ASo1h5VosTSABtQBKLBgeoaWQexYQrRCMNfV",
    "mergePool": "7bNbHeLRyfTgALkHqRs5bzddUwXgfzBQ1Atjk5BK3uY8",
    "quarry": "8RyD4nFiZ56nVNtHM3wBfn2kr889XBrxv8Y1swJq91md",
    "reserves": [
      "BKWm4TRnTeKwfWXRyuzjRHU7iZDkPuXBX5b5V5jSVfGJ",
      "A5Ww74HVrkj9nPeC7pHKLfgeDMEhBCpW1efQdz3TGLEg"
    ],
    "swapAccount": "AURHmCnNwiW4uA2Qj1XvEh4iKgRUZYXtiY7FKAapUV5Y",
    "swapAuthority": "GzGGc1xo457qnjmTbjMx1J7mabMSJs3VQyGnb51Yho1U"
  },
  "currency": "SOL",
  "decimals": 9,
  "displayTokens": [
    "ASoLXbfe7cd6igh5yiEsU8M7FW64QRxPKkxk7sjAfond",
    "So11111111111111111111111111111111111111112"
  ],
  "id": "asol",
  "isVerified": true,
  "name": "aSOL-SOL",
  "sources": [
    "aSOL"
  ],
  "underlyingTokens": [
    "ASoLXbfe7cd6igh5yiEsU8M7FW64QRxPKkxk7sjAfond",
    "So11111111111111111111111111111111111111112"
  ],
  "swapAccountData": {
    "account": {
      "data": {
        "type": "Buffer",
        "data": [
          1,
          0,
          253,
          50,
          0,
          0,
          0,
          0,
          0,
          0,
          0,
          50,
          0,
          0,
          0,
          0,
          0,
          0,
          0,
          0,
          0,
          0,
          0,
          0,
          0,
          0,
          0,
          0,
          0,
          0,
          0,
          0,
          0,
          0,
          0,
          0,
          0,
          0,
          0,
          0,
          0,
          0,
          0,
          0,
          0,
          0,
          0,
          0,
          0,
          0,
          0,
          0,
          0,
          0,
          0,
          0,
          0,
          0,
          0,
          0,
          0,
          0,
          0,
          0,
          0,
          0,
          0,
          0,
          0,
          0,
          0,
          0,
          0,
          0,
          0,
          232,
          131,
          18,
          151,
          47,
          92,
          164,
          134,
          217,
          200,
          100,
          126,
          37,
          254,
          39,
          174,
          34,
          195,
          232,
          19,
          218,
          88,
          86,
          191,
          248,
          14,
          196,
          24,
          10,
          31,
          48,
          52,
          153,
          82,
          249,
          33,
          138,
          221,
          130,
          66,
          124,
          14,
          16,
          245,
          157,
          227,
          1,
          132,
          110,
          246,
          149,
          177,
          230,
          141,
          151,
          234,
          13,
          184,
          196,
          39,
          152,
          146,
          156,
          255,
          134,
          225,
          89,
          201,
          243,
          218,
          150,
          37,
          120,
          155,
          39,
          254,
          167,
          150,
          201,
          176,
          218,
          107,
          104,
          124,
          161,
          92,
          96,
          107,
          76,
          54,
          250,
          108,
          125,
          106,
          89,
          61,
          138,
          176,
          59,
          135,
          89,
          180,
          204,
          44,
          42,
          241,
          199,
          68,
          205,
          48,
          90,
          14,
          22,
          37,
          176,
          4,
          174,
          37,
          247,
          111,
          162,
          123,
          8,
          111,
          151,
          94,
          51,
          60,
          140,
          85,
          24,
          122,
          94,
          236,
          69,
          215,
          220,
          137,
          113,
          219,
          138,
          36,
          194,
          110,
          109,
          56,
          120,
          215,
          222,
          250,
          118,
          172,
          199,
          112,
          116,
          169,
          185,
          197,
          191,
          14,
          6,
          155,
          136,
          87,
          254,
          171,
          129,
          132,
          251,
          104,
          127,
          99,
          70,
          24,
          192,
          53,
          218,
          196,
          57,
          220,
          26,
          235,
          59,
          85,
          152,
          160,
          240,
          0,
          0,
          0,
          0,
          1,
          54,
          20,
          175,
          166,
          168,
          26,
          74,
          140,
          149,
          104,
          132,
          70,
          205,
          165,
          37,
          175,
          12,
          80,
          241,
          158,
          183,
          31,
          12,
          237,
          65,
          247,
          214,
          30,
          85,
          212,
          152,
          44,
          155,
          82,
          69,
          90,
          31,
          169,
          140,
          154,
          32,
          173,
          135,
          86,
          28,
          250,
          68,
          47,
          41,
          49,
          108,
          107,
          12,
          84,
          167,
          154,
          90,
          55,
          221,
          114,
          230,
          51,
          249,
          161,
          0,
          0,
          0,
          0,
          0,
          0,
          0,
          0,
          16,
          39,
          0,
          0,
          0,
          0,
          0,
          0,
          0,
          0,
          0,
          0,
          0,
          0,
          0,
          0,
          16,
          39,
          0,
          0,
          0,
          0,
          0,
          0,
          4,
          0,
          0,
          0,
          0,
          0,
          0,
          0,
          16,
          39,
          0,
          0,
          0,
          0,
          0,
          0,
          0,
          0,
          0,
          0,
          0,
          0,
          0,
          0,
          16,
          39,
          0,
          0,
          0,
          0,
          0,
          0
        ]
      },
      "executable": false,
      "lamports": 3640080,
      "owner": "SSwpkEEcbUqx4vtoEByFjSkhKdCT862DNVb52nZg1UZ",
      "rentEpoch": 361,
      "space": 395
    },
    "publicKey": "AURHmCnNwiW4uA2Qj1XvEh4iKgRUZYXtiY7FKAapUV5Y"
  },
  "provider": "saber",
  "other": "So11111111111111111111111111111111111111112",
  "pool_account": "AURHmCnNwiW4uA2Qj1XvEh4iKgRUZYXtiY7FKAapUV5Y",
  "authority": "GzGGc1xo457qnjmTbjMx1J7mabMSJs3VQyGnb51Yho1U",
  "pool_token_mint": "ALP89a89ASo1h5VosTSABtQBKLBgeoaWQexYQrRCMNfV",
  "token_ids": [
    "ASoLXbfe7cd6igh5yiEsU8M7FW64QRxPKkxk7sjAfond",
    "So11111111111111111111111111111111111111112"
  ],
  "tokens": {
    "ASoLXbfe7cd6igh5yiEsU8M7FW64QRxPKkxk7sjAfond": {
      "chainId": 101,
      "address": "ASoLXbfe7cd6igh5yiEsU8M7FW64QRxPKkxk7sjAfond",
      "symbol": "aSOL",
      "name": "aSOL Aggregate Solana Stake Pool",
      "decimals": 9,
      "logoURI": "https://raw.githubusercontent.com/solana-labs/token-list/main/assets/mainnet/ASoLXbfe7cd6igh5yiEsU8M7FW64QRxPKkxk7sjAfond/logo.svg",
      "extensions": {
        "coingeckoId": "solana",
        "description": "aSOL is the standard for transacting with staked SOL tokens.",
        "github": "https://github.com/aSolHQ",
        "twitter": "https://twitter.com/aSOLprotocol",
        "website": "https://asol.so"
      },
      "addr": "BKWm4TRnTeKwfWXRyuzjRHU7iZDkPuXBX5b5V5jSVfGJ",
      "tag": "",
      "mint": "ASoLXbfe7cd6igh5yiEsU8M7FW64QRxPKkxk7sjAfond",
      "scale": 9
    },
    "So11111111111111111111111111111111111111112": {
      "chainId": 102,
      "address": "So11111111111111111111111111111111111111112",
      "symbol": "wSOL",
      "name": "Wrapped SOL",
      "decimals": 9,
      "logoURI": "https://raw.githubusercontent.com/solana-labs/token-list/main/assets/mainnet/So11111111111111111111111111111111111111112/logo.png",
      "extensions": {
        "coingeckoId": "solana",
        "website": "https://www.solana.com/"
      },
      "addr": "A5Ww74HVrkj9nPeC7pHKLfgeDMEhBCpW1efQdz3TGLEg",
      "tag": "",
      "mint": "So11111111111111111111111111111111111111112",
      "scale": 9
    }
  },
  "fee_accounts": {
    "ASoLXbfe7cd6igh5yiEsU8M7FW64QRxPKkxk7sjAfond": "4e7K1sRxauEPf6XnTnnnbSKi4zjda2LyChpQB4qPJYTd",
    "So11111111111111111111111111111111111111112": "BTJxL7z9CzGEvNo9oN2keWykFfErcVnBqMMZa1BNU31J"
  },
  "target_amp": 100,
  "fee_numerator": 5,
  "fee_denominator": 10000
}